__init__.py
ciccio.py
test_unimore_math.py
my_math/__init__.py
my_math/unimore_math.py
pippo/__init__.py
pippo/peppia.py
my_math_unimore_cicd-0.4.dist-info/METADATA
my_math_unimore_cicd-0.4.dist-info/WHEEL
my_math_unimore_cicd-0.4.dist-info/top_level.txt
my_math_unimore_cicd-0.4.dist-info/RECORD
