Metadata-Version: 2.1
Name: my_math_unimore_cicd
Version: 0.4
Summary: A sample Python package to test CI/CD
Author: Angelo Ferrando
Author-email: angelo.ferrando42@gmail.com
Requires-Dist: pytest
